[
    {
        "patient_id": "p040",
        "date": "2025-07-18",
        "time": "10:00",
        "doctor": "Dr. Usman Malik",
        "status": "booked",
        "patient_name": "Unknown"
    },
    {
        "patient_id": "p051",
        "date": "2025-07-18",
        "time": "11:00",
        "doctor": "Dr. Sarah Ahmed",
        "status": "booked",
        "patient_name": "Unknown"
    },
    {
        "patient_id": "p051",
        "date": "2025-07-18",
        "time": "12:00",
        "doctor": "Dr. Ali Raza",
        "status": "booked",
        "patient_name": "Unknown"
    },
    {
        "patient_id": "p051",
        "date": "2025-07-18",
        "time": "13:00",
        "doctor": "Dr. Muneeb Ahmed",
        "status": "booked",
        "patient_name": "Unknown"
    },
    {
        "patient_id": "p051",
        "date": "2025-07-18",
        "time": "9:00",
        "doctor": "Dr. Farah Siddiqui",
        "status": "booked",
        "patient_name": "Unknown"
    },
    {
        "patient_id": "p051",
        "date": "2025-07-18",
        "time": "10:00",
        "doctor": "Dr. Usman Malik",
        "status": "booked",
        "patient_name": "Unknown"
    },
    {
        "patient_id": "p051",
        "date": "2025-07-18",
        "time": "11:00",
        "doctor": "Dr. Sarah Ahmed",
        "status": "booked",
        "patient_name": "Unknown"
    },
    {
        "patient_id": "P001",
        "date": "2025-07-18",
        "time": "12:00",
        "doctor": "Dr. Ali Raza",
        "status": "booked",
        "patient_name": "Patient 1"
    },
    {
        "patient_id": "P011",
        "date": "2025-07-19",
        "time": "13:00",
        "doctor": "Dr. Muneeb Ahmed",
        "status": "booked",
        "patient_name": "Patient 11"
    },
    {
        "patient_id": "p051",
        "date": "2025-07-20",
        "time": "9:00",
        "doctor": "Dr. Farah Siddiqui",
        "status": "booked",
        "patient_name": "Unknown"
    },
    {
        "patient_id": "p051",
        "date": "2025-07-21",
        "time": "10:00",
        "doctor": "Dr. Usman Malik",
        "status": "booked",
        "patient_name": "Unknown"
    },
    {
        "patient_id": "po40",
        "date": "2025-07-22",
        "time": "11:00",
        "doctor": "Dr. Sarah Khan",
        "status": "booked",
        "patient_name": "Unknown"
    },
    {
        "patient_id": "P045",
        "date": "2025-07-23",
        "time": "12:00",
        "doctor": "Dr. Ali Raza",
        "status": "booked",
        "patient_name": "Fazlu"
    },
    {
        "patient_id": null,
        "date": "2025-07-24",
        "time": "13:00",
        "doctor": "Dr. Muneeb Ahmed",
        "status": "available",
        "patient_name": null
    },
    {
        "patient_id": "P050",
        "date": "2025-07-25",
        "time": "9:00",
        "doctor": "Dr. Farah Siddiqui",
        "status": "booked",
        "patient_name": "Unknown"
    },
    {
        "patient_id": "P0016",
        "date": "2025-07-26",
        "time": "10:00",
        "doctor": "Dr. Usman Malik",
        "status": "booked",
        "patient_name": "Unknown"
    },
    {
        "patient_id": null,
        "date": "2025-07-27",
        "time": "11:00",
        "doctor": "Dr. Sarah Khan",
        "status": "available",
        "patient_name": null
    },
    {
        "patient_id": null,
        "date": "2025-07-28",
        "time": "12:00",
        "doctor": "Dr. Ali Raza",
        "status": "available",
        "patient_name": null
    },
    {
        "patient_id": "P0019",
        "date": "2025-07-29",
        "time": "13:00",
        "doctor": "Dr. Muneeb Ahmed",
        "status": "booked",
        "patient_name": "Unknown"
    },
    {
        "patient_id": "P99",
        "date": "2025-07-30",
        "time": "9:00",
        "doctor": "Dr. Farah Siddiqui",
        "status": "booked",
        "patient_name": "Unknown"
    },
    {
        "patient_id": null,
        "date": "2025-07-28",
        "time": "12:00",
        "doctor": " Dr. Hira Fatima",
        "status": "available",
        "patient_name": null
    },
    {
        "patient_id": null,
        "date": "2025-07-29",
        "time": "13:00",
        "doctor": "Dr. Imran Qureshi",
        "status": "booked",
        "patient_name": "Unknown"
    },
    {
        "patient_id": "p051",
        "date": "2025-07-30",
        "time": "9:00",
        "doctor": "Dr. Amina Bukhari",
        "status": "booked",
        "patient_name": "Unknown"
    },
    {
        "patient_id": "p051",
        "date": "2025-07-31",
        "time": "10:00",
        "doctor": "Dr. Taimoor Hassan",
        "status": "booked",
        "patient_name": "Unknown"
    }
]